quads.py
quads-1.1.0.dist-info/LICENSE
quads-1.1.0.dist-info/WHEEL
quads-1.1.0.dist-info/METADATA
quads-1.1.0.dist-info/RECORD
