Metadata-Version: 2.1
Name: quads
Version: 1.1.0
Summary: A pure Python Quadtree implementation.
Home-page: https://github.com/toastdriven/quads
License: BSD-3-Clause
Author: Daniel Lindsley
Author-email: daniel@toastdriven.com
Requires-Python: >=3.7,<4.0
Classifier: License :: OSI Approved :: BSD License
Classifier: Programming Language :: Python :: 3
Classifier: Programming Language :: Python :: 3.7
Classifier: Programming Language :: Python :: 3.8
Project-URL: Repository, https://github.com/toastdriven/quads
